{
  "short_id": "AI_BATCH_20260320_8c6fd989",
  "batch_id": "BATCH_20260320_2250",
  "news_id": "NEWS_1",
  "segment": {
    "id": 1,
    "title": "Meta AI agent’s instruction causes large sensitive data leak to employees | AI (artificial intelligence) - The Guardian",
    "script": "Breaking news update just in.",
    "visual_keywords": [
      "Meta AI agent’s instruction causes large sensitive data leak to employees | AI (artificial intelligence) - The Guardian headline",
      "AI news footage",
      "breaking news graphics"
    ],
    "duration_target": "15-18s",
    "transition_type": "cut",
    "transition_trigger": true
  }
}